ez_timer/__init__.py
ez_timer/timer.py
ez_timer/timer_test.py
ez_timer-0.0.2.dist-info/METADATA
ez_timer-0.0.2.dist-info/WHEEL
ez_timer-0.0.2.dist-info/top_level.txt
ez_timer-0.0.2.dist-info/RECORD
