Metadata-Version: 2.1
Name: ez-timer
Version: 0.0.2
Summary: The simplest way to time a block of code.
Home-page: https://github.com/lukewood/ez-timer
Author: Luke Wood
Author-email: lukewoodcs@gmail.com
License: Apache License 2.0
Platform: UNKNOWN
Classifier: Programming Language :: Python
Classifier: Programming Language :: Python :: 3.7
Classifier: Operating System :: Unix
Classifier: Operating System :: Microsoft :: Windows
Classifier: Operating System :: MacOS
Classifier: Topic :: Software Development
Provides-Extra: tests
Requires-Dist: flake8 ; extra == 'tests'
Requires-Dist: isort ; extra == 'tests'
Requires-Dist: black ; extra == 'tests'
Requires-Dist: pytest ; extra == 'tests'
